RedisQuery/AST.py
RedisQuery/Lexer.py
RedisQuery/Parser.py
RedisQuery/ParserState.py
RedisQuery/RedisQuery.py
RedisQuery/__init__.py
redis_query-0.0.1.dist-info/LICENSE
redis_query-0.0.1.dist-info/METADATA
redis_query-0.0.1.dist-info/WHEEL
redis_query-0.0.1.dist-info/top_level.txt
redis_query-0.0.1.dist-info/RECORD
