Metadata-Version: 2.1
Name: redis-query
Version: 0.0.1
Summary: A query language for redis.
Home-page: https://github.com/Kuba663/redis-query
Author: VirtualFox
Author-email: virtualfox@onet.pl
License: GNU GPL V3
Platform: UNKNOWN
Classifier: License :: OSI Approved :: GNU General Public License v3 or later (GPLv3+)
Classifier: Programming Language :: Python :: 3
Classifier: Programming Language :: Python :: 3.7
Classifier: Intended Audience :: Developers
Classifier: Development Status :: 2 - Pre-Alpha
Requires-Dist: redis
Requires-Dist: rejson
Requires-Dist: rply
